.coveragerc
.gitattributes
.gitignore
LICENSE
MANIFEST.in
Makefile
README.md
dev_requirements.txt
pyproject.toml
requirements.txt
setup.cfg
versioneer.py
.github/workflows/pythonpackage.yml
src/csirtg_re/__init__.py
src/csirtg_re/_version.py
src/csirtg_re.egg-info/PKG-INFO
src/csirtg_re.egg-info/SOURCES.txt
src/csirtg_re.egg-info/dependency_links.txt
src/csirtg_re.egg-info/requires.txt
src/csirtg_re.egg-info/top_level.txt
test/test_basics.py