Metadata-Version: 2.4
Name: csirtg-re
Version: 0.3.2
Summary: CSIRTG RegEx Utility
Author-email: Wes Young <wes@csirtgadgets.com>
License: Mozilla Public License Version 2.0
Project-URL: Homepage, https://github.com/csirtgadgets/csirtg-re
Classifier: Programming Language :: Python :: 3.11
Classifier: License :: OSI Approved :: MIT License
Classifier: Operating System :: OS Independent
Classifier: Topic :: Security
License-File: LICENSE
Provides-Extra: dev
Requires-Dist: build; extra == "dev"
Requires-Dist: twine; extra == "dev"
Requires-Dist: flake8; extra == "dev"
Requires-Dist: flake8-bugbear; extra == "dev"
Requires-Dist: flake8-comprehensions; extra == "dev"
Requires-Dist: mypy; extra == "dev"
Provides-Extra: test
Requires-Dist: coverage; extra == "test"
Requires-Dist: pytest; extra == "test"
Provides-Extra: all
Requires-Dist: csirtg-re[dev,test]; extra == "all"
Dynamic: license-file
